Metadata-Version: 2.1
Name: hairyBH
Version: 0.1.2
Summary: A package to calculate some important parameters of hairy black holes
Home-page: https://github.com/Skylines316/hairyBH
Author: Weyner Ccuiro
Author-email: wey.090300@gmail.com
License: MIT
Download-URL: https://github.com/Skylines316/hairyBH/tarball/0.1.2
Keywords: blackholes,hairy,geodesics
Platform: UNKNOWN
